text_anonymizer/__init__.py
text_anonymizer/core.py
text_anonymizer/main.py
text_anonymizer-0.1.0.dist-info/LICENSE
text_anonymizer-0.1.0.dist-info/METADATA
text_anonymizer-0.1.0.dist-info/WHEEL
text_anonymizer-0.1.0.dist-info/entry_points.txt
text_anonymizer-0.1.0.dist-info/RECORD
