Metadata-Version: 2.1
Name: text-anonymizer
Version: 0.1.0
Summary: A Python library for anonymizing and de-anonymizing text
Home-page: https://github.com/viktorbezdek/text-anonymizer
License: MIT
Keywords: anonymization,nlp,text-processing
Author: Viktor Bezdek
Author-email: viktor.bezdek@gmail.com
Requires-Python: >=3.8,<4.0
Classifier: Development Status :: 3 - Alpha
Classifier: Intended Audience :: Developers
Classifier: License :: OSI Approved :: MIT License
Classifier: Programming Language :: Python :: 3
Classifier: Programming Language :: Python :: 3.8
Classifier: Programming Language :: Python :: 3.9
Classifier: Programming Language :: Python :: 3.10
Classifier: Programming Language :: Python :: 3.11
Classifier: Programming Language :: Python :: 3.12
Requires-Dist: spacy (>=3.7.6,<4.0.0)
Project-URL: Documentation, https://text-anonymizer.readthedocs.io
Project-URL: Repository, https://github.com/viktorbezdek/text-anonymizer
